odoo/addons/base_google_map/README.rst
odoo/addons/base_google_map/__init__.py
odoo/addons/base_google_map/__manifest__.py
odoo/addons/base_google_map/controllers/__init__.py
odoo/addons/base_google_map/controllers/main.py
odoo/addons/base_google_map/data/google_maps_libraries.xml
odoo/addons/base_google_map/i18n/base_google_map.pot
odoo/addons/base_google_map/i18n/web_google_maps.pot
odoo/addons/base_google_map/models/__init__.py
odoo/addons/base_google_map/models/res_config_settings.py
odoo/addons/base_google_map/readme/CONFIGURE.rst
odoo/addons/base_google_map/readme/CONTRIBUTORS.rst
odoo/addons/base_google_map/readme/CREDITS.rst
odoo/addons/base_google_map/readme/DESCRIPTION.rst
odoo/addons/base_google_map/static/description/icon.png
odoo/addons/base_google_map/static/description/icon.svg
odoo/addons/base_google_map/static/description/index.html
odoo/addons/base_google_map/static/description/thumbnails.png
odoo/addons/base_google_map/views/res_config_settings.xml
odoo12_addon_base_google_map-12.0.1.1.0.dist-info/METADATA
odoo12_addon_base_google_map-12.0.1.1.0.dist-info/WHEEL
odoo12_addon_base_google_map-12.0.1.1.0.dist-info/top_level.txt
odoo12_addon_base_google_map-12.0.1.1.0.dist-info/RECORD
